apn_validators/__init__.py
apn_validators/rules/__init__.py
apn_validators/rules/date_validators.py
apn_validators/rules/file_validators.py
apn_validators/rules/number_validators.py
apn_validators/rules/pattern_validators.py
apn_validators/rules/string_validators.py
apn_validators-0.4.1.dist-info/LICENSE
apn_validators-0.4.1.dist-info/METADATA
apn_validators-0.4.1.dist-info/WHEEL
apn_validators-0.4.1.dist-info/top_level.txt
apn_validators-0.4.1.dist-info/RECORD
