Metadata-Version: 2.1
Name: apn-validators
Version: 0.4.1
Summary: Tools for validating user data and input in Python.
Author-email: Agung PN <agungpndevs@gmail.com>
License: MIT License
Project-URL: Repository, https://github.com/AgungPN/apn-validators
Project-URL: Documentation, https://github.com/AgungPN/apn-validators#readme
Project-URL: Bug Tracker, https://github.com/AgungPN/apn-validators/issues
Project-URL: Changelog, https://github.com/AgungPN/apn-validators/releases
Keywords: validation,validators,python-validator,input-validation,data-validation,pypi
Classifier: Development Status :: 4 - Beta
Classifier: Intended Audience :: Developers
Classifier: License :: OSI Approved :: MIT License
Classifier: Programming Language :: Python
Classifier: Programming Language :: Python :: 3
Classifier: Programming Language :: Python :: 3.6
Classifier: Programming Language :: Python :: 3.7
Classifier: Programming Language :: Python :: 3.8
Classifier: Programming Language :: Python :: 3.9
Classifier: Programming Language :: Python :: 3.10
Classifier: Programming Language :: Python :: 3.11
Classifier: Programming Language :: Python :: 3.12
Classifier: Topic :: Software Development :: Libraries :: Python Modules
Classifier: Typing :: Typed
Requires-Python: >=3.6
License-File: LICENSE
